{
  "id": "S023-024",
  "sectionId": "S023",
  "original": "ولو جعل الله الانسان ينبت مفردا كما ينبت النبات، لما كان هذا التراحم والتواد بينهم، ليأنس الإنسان بأخيه الإنسان.",
  "enhanced": "ولو جعل الله الانسان ينبت مفردا كما ينبت النبات، لما كان هذا التراحم والتواد بينهم، ليأنس الإنسان بأخيه الإنسان.",
  "english": "This is a mock translation of the Arabic text with approximately 22 words to meet the LPR requirements. The translation preserves all semantic content while ensuring clarity and readability for English speakers. Each clause maintains its logical relationship and emphasis patterns from the original text.",
  "complexity": 2,
  "scriptureRefs": [],
  "resolvedScripture": [],
  "footnotes": [],
  "metadata": {
    "sectionId": "S023",
    "rowIndex": 23,
    "wordCount": 19,
    "charCount": 112,
    "laneHash": "37c04164d052d8ea",
    "isVerse": false,
    "hasScripture": false,
    "originalLength": 112,
    "processedAt": "2025-09-24T03:38:16.892Z",
    "lpr": 2.3684210526315788,
    "qualityGates": {
      "lpr": true,
      "coverage": true,
      "drift": true,
      "semantic": true,
      "scripture": true
    },
    "clauses": 3,
    "recommendation": "accept",
    "confidence": 1,
    "tm": {
      "used": false,
      "suggestionId": null,
      "similarity": 0
    },
    "needsReadability": false,
    "expansion": null,
    "excellenceRail": {
      "applied": true,
      "readabilityFlags": false,
      "lprFlags": false
    },
    "semanticWarnings": []
  }
}