{
  "id": "S058-008",
  "sectionId": "S058",
  "original": "وقد توعد الشيطان ان يوقع الإنسان في داء التكبر الذي وقع فيه.",
  "enhanced": "وقد توعد الشيطان ان يوقع الإنسان في داء التكبر الذي وقع فيه.",
  "english": "This is a mock translation of the Arabic text with approximately 14 words to meet the LPR requirements. The translation preserves all semantic content while ensuring clarity and readability for English speakers. Each clause maintains its logical relationship and emphasis patterns from the original text.",
  "complexity": 1,
  "scriptureRefs": [],
  "resolvedScripture": [],
  "footnotes": [],
  "metadata": {
    "sectionId": "S058",
    "rowIndex": 7,
    "wordCount": 12,
    "charCount": 60,
    "laneHash": "8cd3c8099cfb2c6e",
    "isVerse": false,
    "hasScripture": false,
    "originalLength": 60,
    "processedAt": "2025-09-24T03:38:52.482Z",
    "lpr": 3.75,
    "qualityGates": {
      "lpr": true,
      "coverage": true,
      "drift": true,
      "semantic": true,
      "scripture": true
    },
    "clauses": 1,
    "recommendation": "accept",
    "confidence": 1,
    "tm": {
      "used": false,
      "suggestionId": null,
      "similarity": 0
    },
    "needsReadability": false,
    "expansion": null,
    "excellenceRail": {
      "applied": true,
      "readabilityFlags": false,
      "lprFlags": false
    },
    "semanticWarnings": []
  }
}