{
  "id": "S063-005",
  "sectionId": "S063",
  "original": "إلا من استبرئ من داء التكبر من المتقين الذين لا يتبعون خطوات الشيطان ومكره.",
  "enhanced": "إلا من استبرئ من داء التكبر من المتقين الذين لا يتبعون خطوات الشيطان ومكره.",
  "english": "This is a mock translation of the Arabic text with approximately 16 words to meet the LPR requirements. The translation preserves all semantic content while ensuring clarity and readability for English speakers. Each clause maintains its logical relationship and emphasis patterns from the original text.",
  "complexity": 1,
  "scriptureRefs": [],
  "resolvedScripture": [],
  "footnotes": [],
  "metadata": {
    "sectionId": "S063",
    "rowIndex": 4,
    "wordCount": 14,
    "charCount": 75,
    "laneHash": "a1e3448061f58f03",
    "isVerse": false,
    "hasScripture": false,
    "originalLength": 75,
    "processedAt": "2025-09-24T03:38:59.268Z",
    "lpr": 3.2142857142857144,
    "qualityGates": {
      "lpr": true,
      "coverage": true,
      "drift": true,
      "semantic": true,
      "scripture": true
    },
    "clauses": 1,
    "recommendation": "accept",
    "confidence": 1,
    "tm": {
      "used": false,
      "suggestionId": null,
      "similarity": 0
    },
    "needsReadability": false,
    "expansion": null,
    "excellenceRail": {
      "applied": true,
      "readabilityFlags": false,
      "lprFlags": false
    },
    "semanticWarnings": []
  }
}